{
    "$schema": "https://json-schema.org/draft/2020-12/schema",
    "title": "OpenRTB Bid Response with a Transmission Response",
    "description": "An Open RTB Bid Response according to the 2.5 OpenRTB specification. OpenRTB specifies fields unused in the integration of the Transmission Response. Therefore, they are omitted on purpose here.",
    "$id": "openrtb-bid-response",
    "type": "object",
    "properties": {
        "seatbid": {
            "type": "array",
            "description": "Represents a specific seat that provides at least one bid.",
            "items": {
                "type": "object",
                "properties": {
                    "ext": {
                        "type": "object",
                        "description": "Placeholder for exchange-specific extensions to OpenRTB.",
                        "properties": {
                            "paf": {
                                "type": "object",
                                "description": "Dedicated object for PAF as an extension.",
                                "properties": {
                                    "transmission": {
                                        "$ref": "transmission-response.json"
                                    }
                                },
                                "required": [
                                    "transmission"
                                ]
                            }
                        },
                        "required": [
                            "paf"
                        ]
                    }
                },
                "required": [
                    "ext"
                ]
            }
        }
    },
    "required": [
        "seatbid"
    ]
}