{
    "imp": [
        {
            "id": "1",
            "bidfloor": 0.03,
            "banner": {
                "h": 250,
                "w": 300,
                "pos": 0
            },
            "ext": {
                "data": {
                    "paf": {
                        "transaction_id": "4640dc9f-385f-4e02-a0e5-abbf241af94d"
                    }
                }
            }
        }
    ],
    "user": {
        "id": "55816b39711f9b5acf3b90e313ed29e51665623f",
         "ext":
         {
            "eids": 
            [
                {
                    "source": "paf",
                    "uids": [
                        {
                            "source": "paf",
                            "atype": 1,
                            "id": "7435313e-caee-4889-8ad7-0acd0114ae3c",
                            "ext": 
                            {
                                "version": "0.1",
                                "type": "paf_browser_id",
                                "source": {
                                    "domain": "operator0.com",
                                    "timestamp": 1639580000,
                                    "signature": "868e7a6c27b7b7fe5fed219503894bf263f31bb6d8fd48336d283e77b512cda7"
                                }
                            }
                        }
                    ],
                    "ext": {
                        "preferences": {
                            "version": "0.1",
                            "data": { 
                                "use_browsing_for_personalization": true 
                            },
                            "source": {
                                "domain": "cmp1.com",
                                "timestamp": 1639581000,
                                "signature": "65acdcfdbdba8b17936f25a32b33b000393c866588d146cb62ec51ab8890c54f"
                            }
                        }
                    }
                }
            ],
            "paf": {
                "transmission": {
                    "seed": {
                        "version": "0.1",
                        "transaction_ids": [ 
                            "4640dc9f-385f-4e02-a0e5-abbf241af94d", 
                            "7d71a23a-fafa-449a-8b85-63a634780107" 
                        ],
                        "publisher": "publisher.com",
                        "source": {
                            "domain": "publisher.com",
                            "timestamp": 1639582000,
                            "signature": "f1f4871d48b825931c5016a433cb3b6388f989fac363af09b9ee3cd400d86b74"
                        }
                    },
                    "parents": []
                }
            }
        }
    }
}